net_models/__init__.py
net_models/config.py
net_models/exceptions/__init__.py
net_models/fields/Fields.py
net_models/fields/InterfaceNames.py
net_models/fields/__init__.py
net_models/inventory/Config.py
net_models/inventory/ConfigDefaults.py
net_models/inventory/InventoryModels.py
net_models/inventory/NornirInventoryModels.py
net_models/inventory/__init__.py
net_models/loaders/BaseLoader.py
net_models/loaders/DirectoryLoader.py
net_models/loaders/ExcelLoader.py
net_models/loaders/InventoryDumpers.py
net_models/loaders/__init__.py
net_models/models/__init__.py
net_models/models/BaseModels/BaseNetModels.py
net_models/models/BaseModels/SharedModels.py
net_models/models/BaseModels/__init__.py
net_models/models/interfaces/InterfaceCommon.py
net_models/models/interfaces/InterfaceModels.py
net_models/models/interfaces/L2InterfaceModels.py
net_models/models/interfaces/L3InterfaceModels.py
net_models/models/interfaces/SpModels.py
net_models/models/interfaces/__init__.py
net_models/models/routing/BgpModels.py
net_models/models/routing/RouteMaps.py
net_models/models/routing/RoutingProtocols.py
net_models/models/routing/RoutingSP.py
net_models/models/routing/StaticRoutes.py
net_models/models/routing/__init__.py
net_models/models/services/AclModels.py
net_models/models/services/NatModels.py
net_models/models/services/NetworkClock.py
net_models/models/services/ServerModels.py
net_models/models/services/__init__.py
net_models/models/services/cisco_ios/AaaMethods.py
net_models/models/services/cisco_ios/IosLineModels.py
net_models/models/services/cisco_ios/__init__.py
net_models/utils/CustomYamlDumper.py
net_models/utils/__init__.py
net_models/utils/decorators.py
net_models/utils/get_logger.py
net_models/utils/interface_utils.py
net_models/utils/ip_summary.py
net_models/validators/__init__.py
net_models/validators/validators.py
tests/BaseTestClass.py
tests/__init__.py
tests/test_AaaMethods.py
tests/test_BgpModels.py
tests/test_Fields.py
tests/test_InterfaceModels.py
net_models-0.3.5.dist-info/LICENSE
net_models-0.3.5.dist-info/METADATA
net_models-0.3.5.dist-info/WHEEL
net_models-0.3.5.dist-info/top_level.txt
net_models-0.3.5.dist-info/RECORD
