Metadata-Version: 2.1
Name: net-models
Version: 0.3.5
Summary: Network Config Models
Home-page: UNKNOWN
Author: Miroslav Hudec <http://github.com/mihudec>
Author-email: UNKNOWN
License: UNKNOWN
Platform: UNKNOWN
Requires-Dist: typing-extensions
Requires-Dist: pydantic
Requires-Dist: diffsync
Requires-Dist: pyyaml
